MANIFEST.in
README.rst
ez_setup.py
setup.py
HAL/HAL.py
HAL/__init__.py
HAL/context.py
HAL/dbtest.py
HAL/mainentry.py
HAL/spam.py
HAL/string.py
HAL/tkgui.py
HAL.egg-info/PKG-INFO
HAL.egg-info/SOURCES.txt
HAL.egg-info/dependency_links.txt
HAL.egg-info/entry_points.txt
HAL.egg-info/requires.txt
HAL.egg-info/top_level.txt
HAL/engine/__init__.py
HAL/engine/base.py
HAL/engine/general.py
HAL/engine/generic.py
HAL/engine/matrix.py
HAL/engine/oneword.py
HAL/engine/plugin.py
HAL/engine/regex.py